{
  "project_info": {
    "project_number": "518312884540",
    "firebase_url": "https://whispwriting-30282.firebaseio.com",
    "project_id": "whispwriting-30282",
    "storage_bucket": "whispwriting-30282.appspot.com"
  },
  "client": [
    {
      "client_info": {
        "mobilesdk_app_id": "1:518312884540:android:aee0204133276c11",
        "android_client_info": {
          "package_name": "net.whispwriting.whispwriting"
        }
      },
      "oauth_client": [
        {
          "client_id": "518312884540-sldhcehpjk2r5u8j53er2emdmh166h7m.apps.googleusercontent.com",
          "client_type": 3
        }
      ],
      "api_key": [
        {
          "current_key": "AIzaSyD-MY9xt-Qa1HHcCwgAGDwiSpubsKvnHn4"
        }
      ],
      "services": {
        "analytics_service": {
          "status": 1
        },
        "appinvite_service": {
          "status": 1,
          "other_platform_oauth_client": []
        },
        "ads_service": {
          "status": 2
        }
      }
    }
  ],
  "configuration_version": "1"
}